wine_semantic_search/__init__.py
wine_semantic_search/config.py
wine_semantic_search/database.py
wine_semantic_search/embedding.py
wine_semantic_search/errors.py
wine_semantic_search/logging_config.py
wine_semantic_search/main.py
wine_semantic_search/models.py
wine_semantic_search/server.py
wine_semantic_search-0.1.1.dist-info/licenses/LICENSE
wine_semantic_search-0.1.1.dist-info/METADATA
wine_semantic_search-0.1.1.dist-info/WHEEL
wine_semantic_search-0.1.1.dist-info/entry_points.txt
wine_semantic_search-0.1.1.dist-info/top_level.txt
wine_semantic_search-0.1.1.dist-info/RECORD
